blitzml/__init__.py
blitzml/tabular/__init__.py
blitzml/tabular/_classification.py
blitzml/tabular/_regression.py
blitzml/tabular/_supervised.py
blitzml/tabular/_timeseries.py
blitzml/unsupervised/__init__.py
blitzml/unsupervised/_clustering.py
blitzml-0.20.0.dist-info/METADATA
blitzml-0.20.0.dist-info/WHEEL
blitzml-0.20.0.dist-info/top_level.txt
blitzml-0.20.0.dist-info/RECORD
