Metadata-Version: 2.1
Name: blitzml
Version: 0.20.0
Summary: A low-code library for machine learning pipelines
Author: AI Team
Author-email: AI Team <CV.Team.CSE.2023@gmail.com>
Project-URL: Homepage, https://github.com/AhmedMohamed25/blitzml
Keywords: ml,machine learning,classification
Classifier: License :: OSI Approved :: MIT License
Classifier: Programming Language :: Python
Classifier: Programming Language :: Python :: 3
Requires-Python: >=3.8
Requires-Dist: joblib >=1.2.0
Requires-Dist: numpy <=1.23.4
Requires-Dist: pandas >=1.5.1
Requires-Dist: scikit-learn >=1.1.3
Requires-Dist: Boruta >=0.3
Requires-Dist: statsmodels <=0.14
Provides-Extra: dev
Requires-Dist: pip-tools ; extra == 'dev'
Requires-Dist: pytest ; extra == 'dev'
